plantilla_programas_python/__init__.py
plantilla_programas_python/plantilla.py
plantilla_programas_python-0.4.0.dist-info/METADATA
plantilla_programas_python-0.4.0.dist-info/WHEEL
plantilla_programas_python-0.4.0.dist-info/top_level.txt
plantilla_programas_python-0.4.0.dist-info/RECORD
