Metadata-Version: 2.1
Name: plantilla-programas-python
Version: 0.4.0
Summary: Plantilla para programas en Python
Home-page: https://github.com/BREKIADATA-SL/plantilla-programas-python
Author: frapercan
Author-email: frapercan1@alum.us.es
License: MIT
Platform: UNKNOWN
Classifier: Development Status :: 2 - Pre-Alpha
Classifier: License :: OSI Approved :: MIT License
Classifier: Programming Language :: Python :: 3.8
